AnsiFmt/__init__.py
AnsiFmt/fmt.py
ansifmt-0.1.0.dist-info/LICENSE
ansifmt-0.1.0.dist-info/METADATA
ansifmt-0.1.0.dist-info/WHEEL
ansifmt-0.1.0.dist-info/top_level.txt
ansifmt-0.1.0.dist-info/RECORD
