Metadata-Version: 2.1
Name: ansifmt
Version: 0.1.0
Summary: ANSI escape sequences to format printed strings
Home-page: https://github.com/khalid151/AnsiFmt
Author: Khalid
Author-email: khalid.y96@outlook.com
License: UNKNOWN
Platform: UNKNOWN
Classifier: Programming Language :: Python :: 3
Classifier: License :: OSI Approved :: MIT License
Classifier: Operating System :: OS Independent
